<annotation>
	<folder>JPEGImages</folder>
	<filename>6725.png</filename>
	<path>C:\Users\40749\Desktop\tupian\JPEGImages\6725.png</path>
	<source>
		<database>Unknown</database>
	</source>
	<size>
		<width>416</width>
		<height>416</height>
		<depth>3</depth>
	</size>
	<segmented>0</segmented>
	<object>
		<name>ren</name>
		<pose>Unspecified</pose>
		<truncated>0</truncated>
		<difficult>0</difficult>
		<bndbox>
			<xmin>280</xmin>
			<ymin>131</ymin>
			<xmax>313</xmax>
			<ymax>212</ymax>
		</bndbox>
	</object>
	<object>
		<name>tou</name>
		<pose>Unspecified</pose>
		<truncated>0</truncated>
		<difficult>0</difficult>
		<bndbox>
			<xmin>289</xmin>
			<ymin>132</ymin>
			<xmax>303</xmax>
			<ymax>146</ymax>
		</bndbox>
	</object>
	<object>
		<name>ren</name>
		<pose>Unspecified</pose>
		<truncated>0</truncated>
		<difficult>0</difficult>
		<bndbox>
			<xmin>80</xmin>
			<ymin>123</ymin>
			<xmax>188</xmax>
			<ymax>355</ymax>
		</bndbox>
	</object>
	<object>
		<name>tou</name>
		<pose>Unspecified</pose>
		<truncated>0</truncated>
		<difficult>0</difficult>
		<bndbox>
			<xmin>107</xmin>
			<ymin>124</ymin>
			<xmax>135</xmax>
			<ymax>154</ymax>
		</bndbox>
	</object>
</annotation>
