<annotation>
	<folder>JPEGImages</folder>
	<filename>7176.png</filename>
	<path>C:\Users\86188\Desktop\11\tupian\JPEGImages\7176.png</path>
	<source>
		<database>Unknown</database>
	</source>
	<size>
		<width>416</width>
		<height>416</height>
		<depth>3</depth>
	</size>
	<segmented>0</segmented>
	<object>
		<name>ren</name>
		<pose>Unspecified</pose>
		<truncated>0</truncated>
		<difficult>0</difficult>
		<bndbox>
			<xmin>17</xmin>
			<ymin>63</ymin>
			<xmax>134</xmax>
			<ymax>337</ymax>
		</bndbox>
	</object>
	<object>
		<name>tou</name>
		<pose>Unspecified</pose>
		<truncated>0</truncated>
		<difficult>0</difficult>
		<bndbox>
			<xmin>66</xmin>
			<ymin>66</ymin>
			<xmax>120</xmax>
			<ymax>129</ymax>
		</bndbox>
	</object>
</annotation>
